{"cameraMode":{"drawMode":0,"name":"Shaded","section":"Shading Mode"},"sceneLighting":true,"audioPlay":false,"sceneViewState":{"m_AlwaysRefresh":false,"showFog":true,"showSkybox":true,"showFlares":true,"showImageEffects":true,"showParticleSystems":true,"showVisualEffectGraphs":true,"m_FxEnabled":true},"in2DMode":false,"pivot":{"x":-2.8616244792938234,"y":-6.739954471588135,"z":-27.85990333557129},"rotation":{"x":0.00930798426270485,"y":0.021901018917560579,"z":-0.0002037830272456631,"w":0.9997220635414124},"size":0.6093028783798218,"orthographic":false}